.gitignore
LICENSE
MANIFEST.in
README.md
ez_setup.py
requirements.txt
setup.py
spooky_hash.egg-info/PKG-INFO
spooky_hash.egg-info/SOURCES.txt
spooky_hash.egg-info/dependency_links.txt
spooky_hash.egg-info/top_level.txt
src/SpookyV2.cpp
src/SpookyV2.h
src/_SpookyV2.pxd
src/spooky_hash.cpp
src/spooky_hash.pyx
tests/test_spooky_hash.py