Metadata-Version: 1.1
Name: spooky-hash
Version: 1.0.1
Summary: Python wrapper for SpookyHash V2
Home-page: https://github.com/sgrankin/spooky_hash
Author: Sergey Grankin
Author-email: UNKNOWN
License: UNKNOWN
Platform: UNKNOWN
Classifier: Development Status :: 4 - Beta
Classifier: Intended Audience :: Developers
Classifier: License :: OSI Approved :: MIT License
Classifier: Programming Language :: Cython
Classifier: Topic :: Software Development :: Libraries
Classifier: Topic :: Software Development
